setup.py
areyoustillthere.egg-info/PKG-INFO
areyoustillthere.egg-info/SOURCES.txt
areyoustillthere.egg-info/dependency_links.txt
areyoustillthere.egg-info/requires.txt
areyoustillthere.egg-info/top_level.txt
ayst/__init__.py
ayst/ayst.py