Metadata-Version: 1.0
Name: areyoustillthere
Version: 0.1.1
Summary: Find dem emails yo.
Home-page: https://github.com/Raynes/areyoustillthere
Author: Anthony Grimes
Author-email: i@raynes.me
License: MIT
Platform: UNKNOWN
